Workbook

Sheet Leeme
A1: Rocco · Modelo de costos, ganancias y punto de equilibrio
A2: Preparado el 07/10/2026 con los datos reales del piloto. Todo se recalcula al cambiar los supuestos.
A4: Cómo usarlo
A5: Celdas en azul | B5: Supuestos que puedes cambiar (precios, costos, mezcla de clientes, conversión).
A6: Celdas en amarillo | B6: Supuestos clave: los que más mueven el resultado. Revísalos con tus facturas.
A7: Celdas en negro | B7: Fórmulas. No las toques.
A8: Celdas en verde | B8: Traen un valor de otra hoja.
A10: Hojas
A11: Supuestos | B11: Precios, límites, costos por mensaje, costos fijos, prueba gratis y fundadores.
A12: Costo por mensaje | B12: Cuánto nos cuesta cada mensaje que el usuario manda (IA + Meta + voz).
A13: Margen por plan | B13: Ganancia por cliente al mes, a precio normal y de fundador, con uso esperado y en el peor caso.
A14: Punto de equilibrio | B14: Cuántos clientes hacen falta para cubrir los costos fijos.
A15: Fundadores (50) | B15: Resultado mensual con los 50 fundadores y después, a precio normal; escenarios de crecimiento.
A16: Prueba gratis | B16: Cuánto cuesta dar la prueba de 14 días y cuánto cuesta conseguir cada cliente que paga, por tipo de persona invitada.
A17: Datos reales | B17: Lo medido en producción con las 4 cuentas del piloto.
A18: Recomendaciones | B18: A quién invitar y qué medir.

Sheet Supuestos
A1: Supuestos
A2: Azul = cámbialo tú · Amarillo = supuesto clave · Fuente al lado de cada número.
A4: Planes (precios de lista, en USD al mes)
A5: Plan | B5: Precio $/mes | C5: Mensajes incluidos/mes | D5: Mezcla de clientes % | E5: Uso esperado % del tope | F5: Fuente
A6: Personal | B6: 5.99 | C6: 120 | D6: 0.6 | E6: 0.7 | F6: Precio y mensajes: packages/core/src/billing/plans.ts. Mezcla y uso: supuesto.
A7: Negocio | B7: 19.99 | C7: 400 | D7: 0.35 | E7: 0.7 | F7: Precio y mensajes: packages/core/src/billing/plans.ts. Mezcla y uso: supuesto.
A8: Negocio Plus | B8: 39.99 | C8: 1000 | D8: 0.05 | E8: 0.6 | F8: Precio y mensajes: packages/core/src/billing/plans.ts. Mezcla y uso: supuesto.
C9: Total mezcla (debe dar 100 %) | D9: =SUM(D6:D8)
A11: Fundadores y recargas
A12: Descuento fundador | B12: 0.4 | C12: Decisión de Javier (07/10/2026): 40 % para los primeros 50.
A13: Meses pagando con precio fundador | B13: 6 | C13: Fundador dura 7 meses desde el registro; el primero (≈) es la prueba gratis.
A14: Cupos de fundador | B14: 50 | C14: Decisión de Javier.
A15: Recarga grande: precio ($) | B15: 4 | C15: +100 mensajes por $4 (plans.ts). La chica (+20 por $1) está en la hoja Margen por plan.
A16: Recarga grande: mensajes | B16: 100 | C16: plans.ts.
A17: % de clientes que compran 1 recarga grande al mes | B17: 0.1 | C17: Supuesto: quien llega al tope y quiere seguir. Conservador: no cuenta las chicas.
A19: Costo variable por mensaje del usuario
A20: IA por mensaje entrante ($) | B20: ='Datos reales'!J9 | C20: Medido: costo de IA / mensajes entrantes del piloto (hoja Datos reales).
A21: Respuestas por mensaje entrante | B21: ='Datos reales'!K9 | C21: Medido en el piloto (≈1 respuesta por mensaje).
A22: Meta: costo por respuesta ($) | B22: 0.0113 | C22: Tarifa de servicio Meta para Venezuela desde el 01/10/2026 (respuestas dentro de la ventana de 24 h).
A23: Meta: respuestas gratis al mes (por número) | B23: 1000 | C23: Meta regala 1.000 mensajes de servicio al mes por número.
A24: % de mensajes que son nota de voz | B24: ='Datos reales'!L9 | C24: Medido en el piloto.
A25: Costo por nota de voz ($) | B25: 0.003 | C25: Transcripción (Deepgram), nota típica de 20-25 s. Igual al tope de prueba (trial.ts).
A26: Comisión de cobro (% del ingreso) | B26: 0 | C26: Pago móvil, Zelle y Binance sin comisión hoy. Si usas pasarela, cámbialo.
A27: Impuestos sobre el ingreso (%) | B27: 0 | C27: 0 % mientras sea informal. Si facturas: IVA 16 %; IGTF 3 % en divisas. Consulta a tu contador.
A29: Costos fijos al mes (USD)
A30: Railway (worker del bot) | B30: 8 | C30: Estimado: plan Hobby $5 + uso. Cambia por tu factura.
A31: Supabase (base de datos) | B31: 0 | C31: Plan gratis hoy. Pro: $25/mes cuando crezcas o quieras respaldos diarios.
A32: Vercel (página web y panel) | B32: 20 | C32: Pro $20/mes: el plan gratis de Vercel no permite uso comercial.
A33: Dominio holarocco.com | B33: =11.25/12 | C33: Vercel: $11,25 al año.
A34: Línea Movistar del bot | B34: 3 | C34: Estimado del plan mensual de la línea. Cambia por tu recarga real.
A35: Otros (Sentry, correo, varios) | B35: 0 | C35: Planes gratis hoy.
A36: Total costos fijos | B36: =SUM(B30:B35)
A38: Prueba gratis (beta: 14 días desde el registro o N mensajes, lo que llegue primero)
A39: Días de prueba | B39: 14 | C39: TRIAL_DAYS en plans.ts.
A40: Mensajes de la prueba, Personal | B40: 100 | C40: trialMessages en plans.ts (07/10/2026). Al pasarlos, Rocco deja de registrar.
A41: Mensajes de la prueba, Negocio | B41: 200 | C41: Ídem. Plus: 300. Hay además una red de seguridad en $ (4 / 8 / 12) por si alguien manda muchas fotos.

Sheet Costo por mensaje
A1: Costo por mensaje del usuario
A2: El peor caso cuenta Meta completo; en la hoja Fundadores se descuentan las 1.000 respuestas gratis del mes.
A4: Componente | B4: USD por mensaje | C4: Cómo se calcula
A5: IA (Anthropic) | B5: =Supuestos!B20 | C5: Medido en producción.
A6: Meta (respuesta de Rocco) | B6: =Supuestos!B21*Supuestos!B22 | C6: Respuestas por mensaje × tarifa.
A7: Notas de voz | B7: =Supuestos!B24*Supuestos!B25 | C7: % de notas de voz × costo por nota.
A8: Total por mensaje | B8: =SUM(B5:B7)
A9: Costo por 100 mensajes | B9: =B8*100
A10: Precio mínimo por 100 mensajes para 60 % de margen | B10: =B9/(1-0.6) | C10: Regla del modelo de negocio: precio ≥ 2,5 × el costo en el peor caso.

Sheet Margen por plan
A1: Margen por cliente al mes
A2: Uso esperado = mensajes incluidos × uso esperado %. Peor caso = usa todos sus mensajes.
A4: Plan | B4: Precio lista | C4: Precio fundador | D4: Mensajes incluidos | E4: Mensajes esperados | F4: Costo esperado | G4: Costo peor caso | H4: Margen lista $ | I4: Margen lista % | J4: Margen fundador $ | K4: Margen fundador % | L4: Margen fundador peor caso $
A5: =Supuestos!A6 | B5: =Supuestos!B6 | C5: =B5*(1-Supuestos!$B$12) | D5: =Supuestos!C6 | E5: =D5*Supuestos!E6 | F5: =E5*'Costo por mensaje'!$B$8 | G5: =D5*'Costo por mensaje'!$B$8 | H5: =B5*(1-Supuestos!$B$26-Supuestos!$B$27)-F5 | I5: =IF(B5=0,0,H5/B5) | J5: =C5*(1-Supuestos!$B$26-Supuestos!$B$27)-F5 | K5: =IF(C5=0,0,J5/C5) | L5: =C5*(1-Supuestos!$B$26-Supuestos!$B$27)-G5
A6: =Supuestos!A7 | B6: =Supuestos!B7 | C6: =B6*(1-Supuestos!$B$12) | D6: =Supuestos!C7 | E6: =D6*Supuestos!E7 | F6: =E6*'Costo por mensaje'!$B$8 | G6: =D6*'Costo por mensaje'!$B$8 | H6: =B6*(1-Supuestos!$B$26-Supuestos!$B$27)-F6 | I6: =IF(B6=0,0,H6/B6) | J6: =C6*(1-Supuestos!$B$26-Supuestos!$B$27)-F6 | K6: =IF(C6=0,0,J6/C6) | L6: =C6*(1-Supuestos!$B$26-Supuestos!$B$27)-G6
A7: =Supuestos!A8 | B7: =Supuestos!B8 | C7: =B7*(1-Supuestos!$B$12) | D7: =Supuestos!C8 | E7: =D7*Supuestos!E8 | F7: =E7*'Costo por mensaje'!$B$8 | G7: =D7*'Costo por mensaje'!$B$8 | H7: =B7*(1-Supuestos!$B$26-Supuestos!$B$27)-F7 | I7: =IF(B7=0,0,H7/B7) | J7: =C7*(1-Supuestos!$B$26-Supuestos!$B$27)-F7 | K7: =IF(C7=0,0,J7/C7) | L7: =C7*(1-Supuestos!$B$26-Supuestos!$B$27)-G7
A9: Recarga (+100 mensajes) | B9: =Supuestos!B15 | D9: =Supuestos!B16 | G9: =D9*'Costo por mensaje'!$B$8 | H9: =B9*(1-Supuestos!$B$26-Supuestos!$B$27)-G9 | I9: =IF(B9=0,0,H9/B9)
A10: Recarga chica (+20 mensajes) | B10: 1 | D10: 20 | G10: =D10*'Costo por mensaje'!$B$8 | H10: =B10*(1-Supuestos!$B$26-Supuestos!$B$27)-G10 | I10: =IF(B10=0,0,H10/B10)
A11: Promedio ponderado por la mezcla de clientes | B11: =SUMPRODUCT(B5:B7,Supuestos!D6:D8) | C11: =SUMPRODUCT(C5:C7,Supuestos!D6:D8) | F11: =SUMPRODUCT(F5:F7,Supuestos!D6:D8) | H11: =SUMPRODUCT(H5:H7,Supuestos!D6:D8) | I11: =IF(B11=0,0,H11/B11) | J11: =SUMPRODUCT(J5:J7,Supuestos!D6:D8) | K11: =IF(C11=0,0,J11/C11)
A12: Recarga promedio por cliente (margen) | H12: =Supuestos!B17*H9
A13: Margen total por cliente, con recargas (lista) | H13: =H11+H12
A14: Margen total por cliente, con recargas (fundador) | J14: =J11+H12
A16: Nota: el peor caso del fundador muestra si algún plan pierde plata con el descuento cuando el cliente usa todo. Si sale negativo, baja los mensajes del plan fundador o el descuento.

Sheet Punto de equilibrio
A1: Punto de equilibrio
A2: Clientes que pagan necesarios para cubrir los costos fijos del mes.
A4: Concepto | B4: Precio de lista | C4: Precio fundador
A5: Costos fijos al mes | B5: =Supuestos!B36 | C5: =Supuestos!B36
A6: Margen por cliente al mes (con recargas) | B6: ='Margen por plan'!H13 | C6: ='Margen por plan'!J14
A7: Clientes que pagan para cubrir los fijos | B7: =IF(B6<=0,"no se cubre",-INT(-B5/B6)) | C7: =IF(C6<=0,"no se cubre",-INT(-C5/C6))
A8: Ingreso mensual en el punto de equilibrio | B8: =IF(ISNUMBER(B7),B7*'Margen por plan'!B11,0) | C8: =IF(ISNUMBER(C7),C7*'Margen por plan'!C11,0)
A10: Ganancia mensual según cantidad de clientes que pagan (precio de lista; Meta con sus 1.000 respuestas gratis)
A11: Clientes que pagan | B11: Ingreso | C11: Costo variable | D11: Costos fijos | E11: Ganancia | F11: Margen %
A12: 10 | B12: =A12*('Margen por plan'!$B$11+Supuestos!$B$17*Supuestos!$B$15) | C12: =A12*(SUMPRODUCT(Supuestos!$C$6:$C$8,Supuestos!$D$6:$D$8,Supuestos!$E$6:$E$8)+Supuestos!$B$17*Supuestos!$B$16)*('Costo por mensaje'!$B$5+'Costo por mensaje'!$B$7)+MAX(0,A12*(SUMPRODUCT(Supuestos!$C$6:$C$8,Supuestos!$D$6:$D$8,Supuestos!$E$6:$E$8)+Supuestos!$B$17*Supuestos!$B$16)*Supuestos!$B$21-Supuestos!$B$23)*Supuestos!$B$22+B12*(Supuestos!$B$26+Supuestos!$B$27) | D12: =Supuestos!$B$36 | E12: =B12-C12-D12 | F12: =IF(B12=0,0,E12/B12)
A13: 25 | B13: =A13*('Margen por plan'!$B$11+Supuestos!$B$17*Supuestos!$B$15) | C13: =A13*(SUMPRODUCT(Supuestos!$C$6:$C$8,Supuestos!$D$6:$D$8,Supuestos!$E$6:$E$8)+Supuestos!$B$17*Supuestos!$B$16)*('Costo por mensaje'!$B$5+'Costo por mensaje'!$B$7)+MAX(0,A13*(SUMPRODUCT(Supuestos!$C$6:$C$8,Supuestos!$D$6:$D$8,Supuestos!$E$6:$E$8)+Supuestos!$B$17*Supuestos!$B$16)*Supuestos!$B$21-Supuestos!$B$23)*Supuestos!$B$22+B13*(Supuestos!$B$26+Supuestos!$B$27) | D13: =Supuestos!$B$36 | E13: =B13-C13-D13 | F13: =IF(B13=0,0,E13/B13)
A14: 50 | B14: =A14*('Margen por plan'!$B$11+Supuestos!$B$17*Supuestos!$B$15) | C14: =A14*(SUMPRODUCT(Supuestos!$C$6:$C$8,Supuestos!$D$6:$D$8,Supuestos!$E$6:$E$8)+Supuestos!$B$17*Supuestos!$B$16)*('Costo por mensaje'!$B$5+'Costo por mensaje'!$B$7)+MAX(0,A14*(SUMPRODUCT(Supuestos!$C$6:$C$8,Supuestos!$D$6:$D$8,Supuestos!$E$6:$E$8)+Supuestos!$B$17*Supuestos!$B$16)*Supuestos!$B$21-Supuestos!$B$23)*Supuestos!$B$22+B14*(Supuestos!$B$26+Supuestos!$B$27) | D14: =Supuestos!$B$36 | E14: =B14-C14-D14 | F14: =IF(B14=0,0,E14/B14)
A15: 100 | B15: =A15*('Margen por plan'!$B$11+Supuestos!$B$17*Supuestos!$B$15) | C15: =A15*(SUMPRODUCT(Supuestos!$C$6:$C$8,Supuestos!$D$6:$D$8,Supuestos!$E$6:$E$8)+Supuestos!$B$17*Supuestos!$B$16)*('Costo por mensaje'!$B$5+'Costo por mensaje'!$B$7)+MAX(0,A15*(SUMPRODUCT(Supuestos!$C$6:$C$8,Supuestos!$D$6:$D$8,Supuestos!$E$6:$E$8)+Supuestos!$B$17*Supuestos!$B$16)*Supuestos!$B$21-Supuestos!$B$23)*Supuestos!$B$22+B15*(Supuestos!$B$26+Supuestos!$B$27) | D15: =Supuestos!$B$36 | E15: =B15-C15-D15 | F15: =IF(B15=0,0,E15/B15)
A16: 250 | B16: =A16*('Margen por plan'!$B$11+Supuestos!$B$17*Supuestos!$B$15) | C16: =A16*(SUMPRODUCT(Supuestos!$C$6:$C$8,Supuestos!$D$6:$D$8,Supuestos!$E$6:$E$8)+Supuestos!$B$17*Supuestos!$B$16)*('Costo por mensaje'!$B$5+'Costo por mensaje'!$B$7)+MAX(0,A16*(SUMPRODUCT(Supuestos!$C$6:$C$8,Supuestos!$D$6:$D$8,Supuestos!$E$6:$E$8)+Supuestos!$B$17*Supuestos!$B$16)*Supuestos!$B$21-Supuestos!$B$23)*Supuestos!$B$22+B16*(Supuestos!$B$26+Supuestos!$B$27) | D16: =Supuestos!$B$36 | E16: =B16-C16-D16 | F16: =IF(B16=0,0,E16/B16)
A17: 500 | B17: =A17*('Margen por plan'!$B$11+Supuestos!$B$17*Supuestos!$B$15) | C17: =A17*(SUMPRODUCT(Supuestos!$C$6:$C$8,Supuestos!$D$6:$D$8,Supuestos!$E$6:$E$8)+Supuestos!$B$17*Supuestos!$B$16)*('Costo por mensaje'!$B$5+'Costo por mensaje'!$B$7)+MAX(0,A17*(SUMPRODUCT(Supuestos!$C$6:$C$8,Supuestos!$D$6:$D$8,Supuestos!$E$6:$E$8)+Supuestos!$B$17*Supuestos!$B$16)*Supuestos!$B$21-Supuestos!$B$23)*Supuestos!$B$22+B17*(Supuestos!$B$26+Supuestos!$B$27) | D17: =Supuestos!$B$36 | E17: =B17-C17-D17 | F17: =IF(B17=0,0,E17/B17)
A18: 1000 | B18: =A18*('Margen por plan'!$B$11+Supuestos!$B$17*Supuestos!$B$15) | C18: =A18*(SUMPRODUCT(Supuestos!$C$6:$C$8,Supuestos!$D$6:$D$8,Supuestos!$E$6:$E$8)+Supuestos!$B$17*Supuestos!$B$16)*('Costo por mensaje'!$B$5+'Costo por mensaje'!$B$7)+MAX(0,A18*(SUMPRODUCT(Supuestos!$C$6:$C$8,Supuestos!$D$6:$D$8,Supuestos!$E$6:$E$8)+Supuestos!$B$17*Supuestos!$B$16)*Supuestos!$B$21-Supuestos!$B$23)*Supuestos!$B$22+B18*(Supuestos!$B$26+Supuestos!$B$27) | D18: =Supuestos!$B$36 | E18: =B18-C18-D18 | F18: =IF(B18=0,0,E18/B18)
A19: 2000 | B19: =A19*('Margen por plan'!$B$11+Supuestos!$B$17*Supuestos!$B$15) | C19: =A19*(SUMPRODUCT(Supuestos!$C$6:$C$8,Supuestos!$D$6:$D$8,Supuestos!$E$6:$E$8)+Supuestos!$B$17*Supuestos!$B$16)*('Costo por mensaje'!$B$5+'Costo por mensaje'!$B$7)+MAX(0,A19*(SUMPRODUCT(Supuestos!$C$6:$C$8,Supuestos!$D$6:$D$8,Supuestos!$E$6:$E$8)+Supuestos!$B$17*Supuestos!$B$16)*Supuestos!$B$21-Supuestos!$B$23)*Supuestos!$B$22+B19*(Supuestos!$B$26+Supuestos!$B$27) | D19: =Supuestos!$B$36 | E19: =B19-C19-D19 | F19: =IF(B19=0,0,E19/B19)

Sheet Fundadores (50)
A1: Los 50 fundadores: resultado mensual
A2: Mensajes esperados según la mezcla y el uso. Meta descuenta sus 1.000 respuestas gratis del mes.
A4: Concepto | B4: Con precio fundador | C4: Al terminar el descuento (lista) | D4: Nota
A5: Clientes fundadores que pagan | B5: =Supuestos!B14 | C5: =Supuestos!B14 | D5: Todos los cupos llenos y pagando.
A6: Personal | B6: =B5*Supuestos!$D$6 | C6: =C5*Supuestos!$D$6 | D6: Según la mezcla.
A7: Negocio | B7: =B5*Supuestos!$D$7 | C7: =C5*Supuestos!$D$7
A8: Negocio Plus | B8: =B5*Supuestos!$D$8 | C8: =C5*Supuestos!$D$8
A9: Ingreso de planes | B9: =B6*'Margen por plan'!$C$5+B7*'Margen por plan'!$C$6+B8*'Margen por plan'!$C$7 | C9: =C6*'Margen por plan'!$B$5+C7*'Margen por plan'!$B$6+C8*'Margen por plan'!$B$7
A10: Ingreso de recargas | B10: =B5*Supuestos!$B$17*Supuestos!$B$15 | C10: =C5*Supuestos!$B$17*Supuestos!$B$15 | D10: Las recargas no tienen descuento.
A11: Ingreso total | B11: =B9+B10 | C11: =C9+C10
A12: Mensajes del mes | B12: =B6*'Margen por plan'!$E$5+B7*'Margen por plan'!$E$6+B8*'Margen por plan'!$E$7+B5*Supuestos!$B$17*Supuestos!$B$16 | C12: =C6*'Margen por plan'!$E$5+C7*'Margen por plan'!$E$6+C8*'Margen por plan'!$E$7+C5*Supuestos!$B$17*Supuestos!$B$16
A13: Costo IA + voz | B13: =B12*('Costo por mensaje'!$B$5+'Costo por mensaje'!$B$7) | C13: =C12*('Costo por mensaje'!$B$5+'Costo por mensaje'!$B$7)
A14: Costo Meta (después de 1.000 gratis) | B14: =MAX(0,B12*Supuestos!$B$21-Supuestos!$B$23)*Supuestos!$B$22 | C14: =MAX(0,C12*Supuestos!$B$21-Supuestos!$B$23)*Supuestos!$B$22
A15: Comisiones e impuestos | B15: =B11*(Supuestos!$B$26+Supuestos!$B$27) | C15: =C11*(Supuestos!$B$26+Supuestos!$B$27)
A16: Costos fijos | B16: =Supuestos!$B$36 | C16: =Supuestos!$B$36
A17: Ganancia del mes | B17: =B11-B13-B14-B15-B16 | C17: =C11-C13-C14-C15-C16
A18: Margen % | B18: =IF(B11=0,0,B17/B11) | C18: =IF(C11=0,0,C17/C11)
A19: Ganancia acumulada en los meses de fundador | B19: =B17*Supuestos!B13 | D19: Meses pagando con descuento × ganancia del mes.
A20: Lo que se deja de ganar por el descuento (en esos meses) | B20: =(C17-B17)*Supuestos!B13 | D20: Costo de la promoción: lo que pagarías por traer 50 clientes.

Sheet Prueba gratis
A1: Cuánto cuesta dar la prueba de 14 días y conseguir cada cliente que paga
A2: Compara tipos de personas a invitar. Cambia los % en azul con lo que vayas midiendo en el CRM (/admin).
A4: Concepto | B4: Amigos en general | C4: Dueños de negocio pequeño | D4: Personas que ya anotan sus gastos | E4: Nota
A5: Personas invitadas | B5: 100 | C5: 30 | D5: 30 | E5: Cuántas invitas de cada tipo.
A6: % que se registra (le escribe a Rocco) | B6: 0.5 | C6: 0.7 | D6: 0.7 | E6: Supuesto. En el CRM: registros iniciados.
A7: % de los registrados que se activa (3+ movimientos el 1er día) | B7: 0.3 | C7: 0.6 | D7: 0.6 | E7: Supuesto. En el CRM: activados.
A8: Mensajes en 14 días de una prueba activa | B8: 120 | C8: 220 | D8: 110 | E8: Piloto: 8 a 16 por día en las cuentas activas.
A9: Mensajes en 14 días de una prueba inactiva | B9: 10 | C9: 10 | D9: 10 | E9: Registro + algunas pruebas.
A10: % de los activos que paga al terminar | B10: 0.2 | C10: 0.4 | D10: 0.35 | E10: Supuesto clave. En el CRM: encuesta del día 12 y pagos.
A11: Plan que eligen (precio fundador) | B11: ='Margen por plan'!C5 | C11: ='Margen por plan'!C6 | D11: ='Margen por plan'!C5 | E11: Amigos y personas: Personal. Dueños: Negocio.
A12: Margen mensual por cliente que paga (fundador) | B12: ='Margen por plan'!J5 | C12: ='Margen por plan'!J6 | D12: ='Margen por plan'!J5 | E12: De la hoja Margen por plan.
A13: Mensajes incluidos en la prueba | B13: =Supuestos!B40 | C13: =Supuestos!B41 | D13: =Supuestos!B40 | E13: Al pasarlos Rocco deja de registrar: ninguna prueba cuesta más.
A14: Registrados | B14: =B5*B6 | C14: =C5*C6 | D14: =D5*D6
A15: Pruebas activas | B15: =B14*B7 | C15: =C14*C7 | D15: =D14*D7
A16: Pruebas inactivas | B16: =B14-B15 | C16: =C14-C15 | D16: =D14-D15
A17: Costo de las pruebas (Meta completo, con el tope) | B17: =(B15*MIN(B8,B13)+B16*MIN(B9,B13))*'Costo por mensaje'!$B$8 | C17: =(C15*MIN(C8,C13)+C16*MIN(C9,C13))*'Costo por mensaje'!$B$8 | D17: =(D15*MIN(D8,D13)+D16*MIN(D9,D13))*'Costo por mensaje'!$B$8
A18: Clientes que pagan | B18: =B15*B10 | C18: =C15*C10 | D18: =D15*D10
A19: Costo por cliente conseguido (CAC) | B19: =IF(B18=0,0,B17/B18) | C19: =IF(C18=0,0,C17/C18) | D19: =IF(D18=0,0,D17/D18)
A20: Meses para recuperar el CAC | B20: =IF(B12<=0,0,B19/B12) | C20: =IF(C12<=0,0,C19/C12) | D20: =IF(D12<=0,0,D19/D12)
A21: Ganancia mensual que aportan esos clientes | B21: =B18*B12 | C21: =C18*C12 | D21: =D18*D12
A22: Costo máximo de una prueba ($) | B22: =B13*'Costo por mensaje'!$B$8 | C22: =C13*'Costo por mensaje'!$B$8 | D22: =D13*'Costo por mensaje'!$B$8
A24: Lectura: el tipo de persona con el CAC más bajo y más clientes que pagan es a quien debes invitar primero. La prueba se mide en mensajes (100 Personal / 200 Negocio): el costo máximo de una prueba está en la fila 22.

Sheet Datos reales
A1: Datos reales del piloto (producción)
A2: Fuente: base de datos de Rocco (Supabase), consulta del 07/10/2026. Mensajes de los usuarios y respuestas de Rocco.
A4: Cuenta | B4: Plan | C4: Días desde el alta | D4: Mensajes del usuario | E4: Notas de voz | F4: Fotos | G4: Respuestas de Rocco | H4: Costo IA ($) | I4: Movimientos anotados | J4: IA por mensaje | K4: Respuestas por mensaje | L4: % notas de voz | M4: Mensajes por día (activos)
A5: Autolavado (piloto 1) | B5: Negocio | C5: 8 | D5: 130 | E5: 9 | F5: 9 | G5: 128 | H5: 1.1234 | I5: 21 | M5: =IF(C5=0,0,D5/C5)
A6: Finanzas personales | B6: Negocio | C6: 7 | D6: 85 | E6: 6 | F6: 12 | G6: 83 | H6: 0.9002 | I6: 22 | M6: =IF(C6=0,0,D6/C6)
A7: Maria | B7: Personal | C7: 1 | D7: 15 | E7: 2 | F7: 0 | G7: 15 | H7: 0.2695 | I7: 0 | M7: =IF(C7=0,0,D7/C7)
A8: Finanzas Personales (sin uso) | B8: Negocio | C8: 2 | D8: 0 | E8: 0 | F8: 0 | G8: 0 | H8: 0 | I8: 0
A9: Totales y promedios | D9: =SUM(D5:D8) | E9: =SUM(E5:E8) | F9: =SUM(F5:F8) | G9: =SUM(G5:G8) | H9: =SUM(H5:H8) | I9: =SUM(I5:I8) | J9: =IF(D9=0,0,H9/D9) | K9: =IF(D9=0,0,G9/D9) | L9: =IF(D9=0,0,E9/D9)
A11: Lectura: las 2 cuentas activas mandan 12 a 16 mensajes por día al principio (entusiasmo de la primera semana). Con el tiempo suele bajar; el modelo usa 70 % del tope.

Sheet Recomendaciones
A1: A quién invitar a probar a Rocco y qué medir
A3: 1. Invita primero a quien maneja plata todos los días | B3: Dueños de bodegas, areperas, autolavados, peluquerías, ventas por Instagram, freelancers que cobran en $ o USDT. Ya tienen el dolor: anotan en cuaderno y convierten a la tasa a mano. Es el grupo con más uso y más conversión (hoja Prueba gratis).
A4: 2. Después, personas que ya llevan sus gastos | B4: Quien usa Excel o una app para sus gastos, o divide cuentas con amigos. Rocco les ahorra trabajo desde el primer día.
A5: 3. Amigos en general, al final y en grupos pequeños | B5: Prueban por curiosidad, usan poco y convierten menos. Son buenos para encontrar errores, no para medir la conversión.
A6: Cuántos invitar | B6: Lotes de 10 a 15 por semana, no 100 de una vez: así puedes acompañar a cada uno, ver en /admin quién se activa y ajustar los textos de Rocco. La prueba se mide en mensajes: el peor caso es ~$2,10 por Personal (100) y ~$4,30 por Negocio (200).
A7: Qué medir cada semana (en /admin) | B7: Registros iniciados vs terminados; activados (3+ movimientos el 1er día); activos en 7 días; respuestas de la encuesta (precio justo y caro); '¿seguimos?' sí / dudas; pagos.
A8: Señales de que vas bien | B8: Activación ≥ 50 %; activos a los 7 días ≥ 40 %; conversión de activos a pago ≥ 25 %; el precio 'justo' de la encuesta en o por encima del precio fundador.
A9: Qué hacer con quien no se activa | B9: Escríbele desde 'Registros sin terminar' o el semáforo rojo: pregúntale qué le frenó. Esa conversación vale más que cualquier encuesta.
A10: Prueba por mensajes y recargas | B10: La prueba son 100 mensajes (Personal) o 200 (Negocio) en 14 días: unos 7 o 14 por día, más que el uso normal. Al llegar al tope del mes, quien quiere más compra recargas: +20 por $1 o +100 por $4. Las dos dejan más del 50 % de margen en el peor caso, así que el power user paga lo que usa y tu margen no cambia.
A11: Antes de escalar | B11: Comprar holarocco.com, pasar Vercel a Pro (uso comercial) y revisar el costo real de la IA por mensaje: es la palanca más grande del margen.
